tracapp/__init__.py
tracapp/exceptions.py
tracapp/logger.py
tracapp/py.typed
tracapp/settings.py
tracapp-0.4.8.dist-info/licenses/LICENSE
tracapp-0.4.8.dist-info/WHEEL
tracapp-0.4.8.dist-info/METADATA
tracapp-0.4.8.dist-info/RECORD
