Metadata-Version: 2.4
Name: tracapp
Version: 0.4.8
Summary: common facilities to be used by Prima services
License-Expression: MIT
License-File: LICENSE
Requires-Dist: billiard>=4.2.1
Requires-Dist: celery>=5.5.3
Requires-Dist: httpx>=0.28.1
Requires-Dist: logfire[celery]>=4.5.0
Requires-Dist: opentelemetry-instrumentation-celery>=0.57b0
Requires-Dist: opentelemetry-instrumentation-httpx>=0.57b0
Requires-Dist: pydantic-ai>=1.0.6
Requires-Dist: pydantic-settings>=2.10.1
Requires-Python: >=3.12
